memoprop/__about__.py
memoprop/__init__.py
memoprop/_version.py
memoprop/decorators.py
memoprop-0.2.0.dist-info/LICENSE
memoprop-0.2.0.dist-info/METADATA
memoprop-0.2.0.dist-info/WHEEL
memoprop-0.2.0.dist-info/top_level.txt
memoprop-0.2.0.dist-info/RECORD
